vampire/__init__.py
vampire/amath.py
vampire/analysis.py
vampire/extraction.py
vampire/model.py
vampire/plot.py
vampire/processing.py
vampire/util.py
vampire_analysis-0.0.1.dist-info/LICENSE
vampire_analysis-0.0.1.dist-info/METADATA
vampire_analysis-0.0.1.dist-info/WHEEL
vampire_analysis-0.0.1.dist-info/top_level.txt
vampire_analysis-0.0.1.dist-info/RECORD
